devanshlibrarey/__init__.py
devanshlibrarey/converters.py
devanshlibrarey-0.1.0.dist-info/METADATA
devanshlibrarey-0.1.0.dist-info/WHEEL
devanshlibrarey-0.1.0.dist-info/top_level.txt
devanshlibrarey-0.1.0.dist-info/RECORD
