Metadata-Version: 2.4
Name: devanshlibrarey
Version: 0.1.0
Summary: Convert Indian number units like lakh to million
Author: Devansh Prajapati
Requires-Python: >=3.8
